materials_compendium/MaterialsCompendium.json
materials_compendium/__init__.py
materials_compendium/parse.py
materials_compendium/utils.py
materials_compendium-0.1.2.dist-info/LICENSE
materials_compendium-0.1.2.dist-info/METADATA
materials_compendium-0.1.2.dist-info/WHEEL
materials_compendium-0.1.2.dist-info/top_level.txt
materials_compendium-0.1.2.dist-info/RECORD
