Metadata-Version: 2.1
Name: materials-compendium
Version: 0.1.2
Summary: Python tools for processing the PNNL Materials Compendium
Author-email: Ahnaf Tahmid Chowdhury <tahmid@nse.mist.ac.bd>
License: BSD 2-Clause License
Project-URL: Bug Tracker, https://github.com/pyne/materials-compendium/issues
Project-URL: Source Code, https://github.com/pyne/materials-compendium
Classifier: Development Status :: 4 - Beta
Classifier: Intended Audience :: Developers
Classifier: Intended Audience :: End Users/Desktop
Classifier: Intended Audience :: Science/Research
Classifier: License :: OSI Approved :: BSD License
Classifier: Natural Language :: English
Classifier: Operating System :: OS Independent
Classifier: Topic :: Scientific/Engineering
Classifier: Programming Language :: Python :: 3
Classifier: Programming Language :: Python :: 3.7
Classifier: Programming Language :: Python :: 3.8
Classifier: Programming Language :: Python :: 3.9
Classifier: Programming Language :: Python :: 3.10
Classifier: Programming Language :: Python :: 3.11
Requires-Python: >=3.7
License-File: LICENSE
Provides-Extra: docs
Requires-Dist: sphinx ; extra == 'docs'
Provides-Extra: test
Requires-Dist: pytest ; extra == 'test'
